my_model/VERSION
my_model/__init__.py
my_model/config.yml
my_model/pipeline.py
my_model/predict.py
my_model/train_pipeline.py
my_model/config/__init__.py
my_model/config/core.py
my_model/datasets/__init__.py
my_model/datasets/test.csv
my_model/datasets/train.csv
my_model/processing/__init__.py
my_model/processing/data_manager.py
my_model/processing/validation.py
my_model/trained_models/pl_insurance.pkl
my_model/trained_models/pl_insurance_0.0.5.pkl
insurance-0.0.5.dist-info/METADATA
insurance-0.0.5.dist-info/WHEEL
insurance-0.0.5.dist-info/top_level.txt
insurance-0.0.5.dist-info/RECORD
